Workbook

Sheet Inventory_Data
A1: SKU | B1: Product Name | C1: Category | D1: Unit Cost | E1: Retail Price | F1: Stock Units | G1: Reorder Level | H1: Units On Order | I1: Total Inventory Value | J1: Margin % | K1: Restock Status
A2: SKU-1001 | B2: Wireless Noise-Canceling Headphones | C2: Electronics | D2: 65 | E2: 129.99 | F2: 120 | G2: 50 | H2: 0 | I2: =D2*F2 -> 7800 | J2: =(E2-D2)/E2 -> 0.49996154 | K2: =IF(F2<=G2,"Needs Reorder","Sufficient") -> Sufficient
A3: SKU-1002 | B3: Mechanical Gaming Keyboard | C3: Electronics | D3: 45.5 | E3: 89.99 | F3: 85 | G3: 40 | H3: 0 | I3: =D3*F3 -> 3867.5 | J3: =(E3-D3)/E3 -> 0.49438827 | K3: =IF(F3<=G3,"Needs Reorder","Sufficient") -> Sufficient
A4: SKU-1003 | B4: Ergonomic Office Chair | C4: Furniture | D4: 110 | E4: 249.5 | F4: 28 | G4: 30 | H4: 25 | I4: =D4*F4 -> 3080 | J4: =(E4-D4)/E4 -> 0.55911824 | K4: =IF(F4<=G4,"Needs Reorder","Sufficient") -> Needs Reorder
A5: SKU-1004 | B5: Motorized Standing Desk | C5: Furniture | D5: 185 | E5: 399 | F5: 15 | G5: 20 | H5: 20 | I5: =D5*F5 -> 2775 | J5: =(E5-D5)/E5 -> 0.53634085 | K5: =IF(F5<=G5,"Needs Reorder","Sufficient") -> Needs Reorder
A6: SKU-1005 | B6: Organic Cotton T-Shirt | C6: Apparel | D6: 8.2 | E6: 24 | F6: 350 | G6: 100 | H6: 0 | I6: =D6*F6 -> 2870 | J6: =(E6-D6)/E6 -> 0.65833333 | K6: =IF(F6<=G6,"Needs Reorder","Sufficient") -> Sufficient
A7: SKU-1006 | B7: Waterproof Trail Jacket | C7: Apparel | D7: 34 | E7: 85 | F7: 65 | G7: 50 | H7: 0 | I7: =D7*F7 -> 2210 | J7: =(E7-D7)/E7 -> 0.6 | K7: =IF(F7<=G7,"Needs Reorder","Sufficient") -> Sufficient
A8: SKU-1007 | B8: Ceramic Pour-Over Coffee Maker | C8: Kitchenware | D8: 14.5 | E8: 36 | F8: 90 | G8: 40 | H8: 0 | I8: =D8*F8 -> 1305 | J8: =(E8-D8)/E8 -> 0.59722222 | K8: =IF(F8<=G8,"Needs Reorder","Sufficient") -> Sufficient
A9: SKU-1008 | B9: Cast Iron Skillet 12-inch | C9: Kitchenware | D9: 22 | E9: 49.99 | F9: 42 | G9: 35 | H9: 0 | I9: =D9*F9 -> 924 | J9: =(E9-D9)/E9 -> 0.55991198 | K9: =IF(F9<=G9,"Needs Reorder","Sufficient") -> Sufficient
A10: SKU-1009 | B10: Smart Fitness Tracker Watch | C10: Electronics | D10: 38 | E10: 79.99 | F10: 18 | G10: 45 | H10: 50 | I10: =D10*F10 -> 684 | J10: =(E10-D10)/E10 -> 0.52494062 | K10: =IF(F10<=G10,"Needs Reorder","Sufficient") -> Needs Reorder
A11: SKU-1010 | B11: Ultra-Fast USB-C Charging Hub | C11: Electronics | D11: 12.5 | E11: 29.99 | F11: 210 | G11: 60 | H11: 0 | I11: =D11*F11 -> 2625 | J11: =(E11-D11)/E11 -> 0.5831944 | K11: =IF(F11<=G11,"Needs Reorder","Sufficient") -> Sufficient
A12: SKU-1011 | B12: Solid Oak Bookshelf 5-Tier | C12: Furniture | D12: 95 | E12: 199 | F12: 12 | G12: 15 | H12: 15 | I12: =D12*F12 -> 1140 | J12: =(E12-D12)/E12 -> 0.52261307 | K12: =IF(F12<=G12,"Needs Reorder","Sufficient") -> Needs Reorder
A13: SKU-1012 | B13: Modern Minimalist Desk Lamp | C13: Furniture | D13: 18 | E13: 42 | F13: 74 | G13: 30 | H13: 0 | I13: =D13*F13 -> 1332 | J13: =(E13-D13)/E13 -> 0.57142857 | K13: =IF(F13<=G13,"Needs Reorder","Sufficient") -> Sufficient
... A35: SKU-1034 | B35: Air Fryer Heat Resistant Mat Set | C35: Kitchenware | D35: 7.2 | E35: 18.5 | F35: 85 | G35: 30 | H35: 0 | I35: =D35*F35 -> 612 | J35: =(E35-D35)/E35 -> 0.61081081 | K35: =IF(F35<=G35,"Needs Reorder","Sufficient") -> Sufficient

Sheet Calc_Data
A1: Metric | B1: Value | C1: Category | D1: Total Value | E1: Total Units | F1: Avg Margin % | G1: Sales Revenue | H1: Selected Category | I1: =Dashboard!D9 -> Furniture | K1: Product Display | L1: Stock Units | M1: Reorder Level | N1: Restock Status | O1: Units Sold (Velocity) | P1: Executive Metric | Q1: Value | R1: Notes / Reference | S1: Channel | T1: Channel Revenue | U1: Channel Profit | V1: Channel Units | W1: Margin %
A2: Total Inventory Value | B2: =SUM(Inventory_Data!I2:I35) -> 62337.5 | C2: Electronics | D2: =SUMIFS(Inventory_Data!I$2:I$35, Inventory_Data!C$2:C$35, C2) -> 27425.5 | E2: =SUMIFS(Inventory_Data!F$2:F$35, Inventory_Data!C$2:C$35, C2) -> 930 | F2: =AVERAGEIFS(Inventory_Data!J$2:J$35, Inventory_Data!C$2:C$35, C2) -> 0.54563811 | G2: =SUMIFS(Sales_Orders!I$2:I$35, Sales_Orders!E$2:E$35, C2) -> 13064.38 | H2: Filtered Inventory Value | I2: =IF(OR(I$1="All Categories", I$1=""), SUM(Inventory_Data!I$2:I$35), SUMIFS(Inventory_Data!I$2:I$35, Inventory_Data!C$2:C$35, I$1)) -> 12571 | K2: =IFERROR(__xludf.DUMMYFUNCTION("IFERROR(INDEX(FILTER(Inventory_Data!B$2:B$35, (Inventory_Data!A$2:A$35<>"""") * IF(OR(I$1=""All Categories"", I$1=""""), 1, (Inventory_Data!C$2:C$35=I$1))), 1), ""-"")"),"Ergonomic Office Chair") -> Ergonomic Office Chair | L2: =IFERROR(__xludf.DUMMYFUNCTION("IFERROR(INDEX(FILTER(Inventory_Data!F$2:F$35, (Inventory_Data!A$2:A$35<>"""") * IF(OR(I$1=""All Categories"", I$1=""""), 1, (Inventory_Data!C$2:C$35=I$1))), 1), 0)"),28.0) -> 28 | M2: =IFERROR(__xludf.DUMMYFUNCTION("IFERROR(INDEX(FILTER(Inventory_Data!G$2:G$35, (Inventory_Data!A$2:A$35<>"""") * IF(OR(I$1=""All Categories"", I$1=""""), 1, (Inventory_Data!C$2:C$35=I$1))), 1), 0)"),30.0) -> 30 | N2: =IFERROR(__xludf.DUMMYFUNCTION("IFERROR(INDEX(FILTER(Inventory_Data!K$2:K$35, (Inventory_Data!A$2:A$35<>"""") * IF(OR(I$1=""All Categories"", I$1=""""), 1, (Inventory_Data!C$2:C$35=I$1))), 1), ""-"")"),"Needs Reorder") -> Needs Reorder | O2: =IF(K2="-", 0, IFERROR(SUMIF(Sales_Orders!D$2:D$35, K2, Sales_Orders!G$2:G$35), 0)) -> 8 | P2: Total Revenue | Q2: =SUM(Sales_Orders!I$2:I$35) -> 35454.49 | R2: Gross Sales | S2: Online Store | T2: =SUMIF(Sales_Orders!F$2:F$35, S2, Sales_Orders!I$2:I$35) -> 14735.72 | U2: =SUMIF(Sales_Orders!F$2:F$35, S2, Sales_Orders!K$2:K$35) -> 8100.72 | V2: =SUMIF(Sales_Orders!F$2:F$35, S2, Sales_Orders!G$2:G$35) -> 250 | W2: =IF(T2>0, U2/T2, 0) -> 0.54973357
A3: Total Units in Stock | B3: =SUM(Inventory_Data!F2:F35) -> 3024 | C3: Furniture | D3: =SUMIFS(Inventory_Data!I$2:I$35, Inventory_Data!C$2:C$35, C3) -> 12571 | E3: =SUMIFS(Inventory_Data!F$2:F$35, Inventory_Data!C$2:C$35, C3) -> 316 | F3: =AVERAGEIFS(Inventory_Data!J$2:J$35, Inventory_Data!C$2:C$35, C3) -> 0.55230257 | G3: =SUMIFS(Sales_Orders!I$2:I$35, Sales_Orders!E$2:E$35, C3) -> 8719.74 | H3: Filtered Stock Units | I3: =IF(OR(I$1="All Categories", I$1=""), SUM(Inventory_Data!F$2:F$35), SUMIFS(Inventory_Data!F$2:F$35, Inventory_Data!C$2:C$35, I$1)) -> 316 | K3: =IFERROR(__xludf.DUMMYFUNCTION("IFERROR(INDEX(FILTER(Inventory_Data!B$2:B$35, (Inventory_Data!A$2:A$35<>"""") * IF(OR(I$1=""All Categories"", I$1=""""), 1, (Inventory_Data!C$2:C$35=I$1))), 2), ""-"")"),"Motorized Standing Desk") -> Motorized Standing Desk | L3: =IFERROR(__xludf.DUMMYFUNCTION("IFERROR(INDEX(FILTER(Inventory_Data!F$2:F$35, (Inventory_Data!A$2:A$35<>"""") * IF(OR(I$1=""All Categories"", I$1=""""), 1, (Inventory_Data!C$2:C$35=I$1))), 2), 0)"),15.0) -> 15 | M3: =IFERROR(__xludf.DUMMYFUNCTION("IFERROR(INDEX(FILTER(Inventory_Data!G$2:G$35, (Inventory_Data!A$2:A$35<>"""") * IF(OR(I$1=""All Categories"", I$1=""""), 1, (Inventory_Data!C$2:C$35=I$1))), 2), 0)"),20.0) -> 20 | N3: =IFERROR(__xludf.DUMMYFUNCTION("IFERROR(INDEX(FILTER(Inventory_Data!K$2:K$35, (Inventory_Data!A$2:A$35<>"""") * IF(OR(I$1=""All Categories"", I$1=""""), 1, (Inventory_Data!C$2:C$35=I$1))), 2), ""-"")"),"Needs Reorder") -> Needs Reorder | O3: =IF(K3="-", 0, IFERROR(SUMIF(Sales_Orders!D$2:D$35, K3, Sales_Orders!G$2:G$35), 0)) -> 5 | P3: Total COGS | Q3: =SUM(Sales_Orders!J$2:J$35) -> 15360.5 | R3: Cost of Goods | S3: Marketplace | T3: =SUMIF(Sales_Orders!F$2:F$35, S3, Sales_Orders!I$2:I$35) -> 6656.13 | U3: =SUMIF(Sales_Orders!F$2:F$35, S3, Sales_Orders!K$2:K$35) -> 3959.63 | V3: =SUMIF(Sales_Orders!F$2:F$35, S3, Sales_Orders!G$2:G$35) -> 231 | W3: =IF(T3>0, U3/T3, 0) -> 0.59488472
A4: Low Stock Items | B4: =COUNTIF(Inventory_Data!K2:K35, "Needs Reorder") -> 11 | C4: Apparel | D4: =SUMIFS(Inventory_Data!I$2:I$35, Inventory_Data!C$2:C$35, C4) -> 11945.5 | E4: =SUMIFS(Inventory_Data!F$2:F$35, Inventory_Data!C$2:C$35, C4) -> 948 | F4: =AVERAGEIFS(Inventory_Data!J$2:J$35, Inventory_Data!C$2:C$35, C4) -> 0.61921738 | G4: =SUMIFS(Sales_Orders!I$2:I$35, Sales_Orders!E$2:E$35, C4) -> 6505 | H4: Filtered Low Stock Items | I4: =IF(OR(I$1="All Categories", I$1=""), COUNTIF(Inventory_Data!K$2:K$35, "Needs Reorder"), COUNTIFS(Inventory_Data!K$2:K$35, "Needs Reorder", Inventory_Data!C$2:C$35, I$1)) -> 5 | K4: =IFERROR(__xludf.DUMMYFUNCTION("IFERROR(INDEX(FILTER(Inventory_Data!B$2:B$35, (Inventory_Data!A$2:A$35<>"""") * IF(OR(I$1=""All Categories"", I$1=""""), 1, (Inventory_Data!C$2:C$35=I$1))), 3), ""-"")"),"Solid Oak Bookshelf 5-Tier") -> Solid Oak Bookshelf 5-Tier | L4: =IFERROR(__xludf.DUMMYFUNCTION("IFERROR(INDEX(FILTER(Inventory_Data!F$2:F$35, (Inventory_Data!A$2:A$35<>"""") * IF(OR(I$1=""All Categories"", I$1=""""), 1, (Inventory_Data!C$2:C$35=I$1))), 3), 0)"),12.0) -> 12 | M4: =IFERROR(__xludf.DUMMYFUNCTION("IFERROR(INDEX(FILTER(Inventory_Data!G$2:G$35, (Inventory_Data!A$2:A$35<>"""") * IF(OR(I$1=""All Categories"", I$1=""""), 1, (Inventory_Data!C$2:C$35=I$1))), 3), 0)"),15.0) -> 15 | N4: =IFERROR(__xludf.DUMMYFUNCTION("IFERROR(INDEX(FILTER(Inventory_Data!K$2:K$35, (Inventory_Data!A$2:A$35<>"""") * IF(OR(I$1=""All Categories"", I$1=""""), 1, (Inventory_Data!C$2:C$35=I$1))), 3), ""-"")"),"Needs Reorder") -> Needs Reorder | O4: =IF(K4="-", 0, IFERROR(SUMIF(Sales_Orders!D$2:D$35, K4, Sales_Orders!G$2:G$35), 0)) -> 6 | P4: Gross Profit | Q4: =SUM(Sales_Orders!K$2:K$35) -> 20093.99 | R4: Net Earnings | S4: Direct B2B | T4: =SUMIF(Sales_Orders!F$2:F$35, S4, Sales_Orders!I$2:I$35) -> 7953.82 | U4: =SUMIF(Sales_Orders!F$2:F$35, S4, Sales_Orders!K$2:K$35) -> 4356.82 | V4: =SUMIF(Sales_Orders!F$2:F$35, S4, Sales_Orders!G$2:G$35) -> 54 | W4: =IF(T4>0, U4/T4, 0) -> 0.54776447
A5: Average Margin | B5: =AVERAGE(Inventory_Data!J2:J35) -> 0.5742193 | C5: Kitchenware | D5: =SUMIFS(Inventory_Data!I$2:I$35, Inventory_Data!C$2:C$35, C5) -> 10395.5 | E5: =SUMIFS(Inventory_Data!F$2:F$35, Inventory_Data!C$2:C$35, C5) -> 830 | F5: =AVERAGEIFS(Inventory_Data!J$2:J$35, Inventory_Data!C$2:C$35, C5) -> 0.59045921 | G5: =SUMIFS(Sales_Orders!I$2:I$35, Sales_Orders!E$2:E$35, C5) -> 7165.37 | H5: Filtered Avg Margin | I5: =IF(OR(I$1="All Categories", I$1=""), AVERAGE(Inventory_Data!J$2:J$35), AVERAGEIFS(Inventory_Data!J$2:J$35, Inventory_Data!C$2:C$35, I$1)) -> 0.55230257 | K5: =IFERROR(__xludf.DUMMYFUNCTION("IFERROR(INDEX(FILTER(Inventory_Data!B$2:B$35, (Inventory_Data!A$2:A$35<>"""") * IF(OR(I$1=""All Categories"", I$1=""""), 1, (Inventory_Data!C$2:C$35=I$1))), 4), ""-"")"),"Modern Minimalist Desk Lamp") -> Modern Minimalist Desk Lamp | L5: =IFERROR(__xludf.DUMMYFUNCTION("IFERROR(INDEX(FILTER(Inventory_Data!F$2:F$35, (Inventory_Data!A$2:A$35<>"""") * IF(OR(I$1=""All Categories"", I$1=""""), 1, (Inventory_Data!C$2:C$35=I$1))), 4), 0)"),74.0) -> 74 | M5: =IFERROR(__xludf.DUMMYFUNCTION("IFERROR(INDEX(FILTER(Inventory_Data!G$2:G$35, (Inventory_Data!A$2:A$35<>"""") * IF(OR(I$1=""All Categories"", I$1=""""), 1, (Inventory_Data!C$2:C$35=I$1))), 4), 0)"),30.0) -> 30 | N5: =IFERROR(__xludf.DUMMYFUNCTION("IFERROR(INDEX(FILTER(Inventory_Data!K$2:K$35, (Inventory_Data!A$2:A$35<>"""") * IF(OR(I$1=""All Categories"", I$1=""""), 1, (Inventory_Data!C$2:C$35=I$1))), 4), ""-"")"),"Sufficient") -> Sufficient | O5: =IF(K5="-", 0, IFERROR(SUMIF(Sales_Orders!D$2:D$35, K5, Sales_Orders!G$2:G$35), 0)) -> 12 | P5: Gross Profit % | Q5: =IF(Q2>0, Q4/Q2, 0) -> 0.56675445 | R5: Margin Rate | S5: Retail Partner | T5: =SUMIF(Sales_Orders!F$2:F$35, S5, Sales_Orders!I$2:I$35) -> 6108.82 | U5: =SUMIF(Sales_Orders!F$2:F$35, S5, Sales_Orders!K$2:K$35) -> 3676.82 | V5: =SUMIF(Sales_Orders!F$2:F$35, S5, Sales_Orders!G$2:G$35) -> 132 | W5: =IF(T5>0, U5/T5, 0) -> 0.60188711
A6: Total SKUs | B6: =COUNTA(Inventory_Data!A2:A35) -> 34 | H6: Filtered SKU Count | I6: =IF(OR(I$1="All Categories", I$1=""), COUNTA(Inventory_Data!A$2:A$35), COUNTIF(Inventory_Data!C$2:C$35, I$1)) -> 8 | K6: =IFERROR(__xludf.DUMMYFUNCTION("IFERROR(INDEX(FILTER(Inventory_Data!B$2:B$35, (Inventory_Data!A$2:A$35<>"""") * IF(OR(I$1=""All Categories"", I$1=""""), 1, (Inventory_Data!C$2:C$35=I$1))), 5), ""-"")"),"Adjustable Laptop Riser") -> Adjustable Laptop Riser | L6: =IFERROR(__xludf.DUMMYFUNCTION("IFERROR(INDEX(FILTER(Inventory_Data!F$2:F$35, (Inventory_Data!A$2:A$35<>"""") * IF(OR(I$1=""All Categories"", I$1=""""), 1, (Inventory_Data!C$2:C$35=I$1))), 5), 0)"),95.0) -> 95 | M6: =IFERROR(__xludf.DUMMYFUNCTION("IFERROR(INDEX(FILTER(Inventory_Data!G$2:G$35, (Inventory_Data!A$2:A$35<>"""") * IF(OR(I$1=""All Categories"", I$1=""""), 1, (Inventory_Data!C$2:C$35=I$1))), 5), 0)"),35.0) -> 35 | N6: =IFERROR(__xludf.DUMMYFUNCTION("IFERROR(INDEX(FILTER(Inventory_Data!K$2:K$35, (Inventory_Data!A$2:A$35<>"""") * IF(OR(I$1=""All Categories"", I$1=""""), 1, (Inventory_Data!C$2:C$35=I$1))), 5), ""-"")"),"Sufficient") -> Sufficient | O6: =IF(K6="-", 0, IFERROR(SUMIF(Sales_Orders!D$2:D$35, K6, Sales_Orders!G$2:G$35), 0)) -> 22 | P6: Total Units Sold | Q6: =SUM(Sales_Orders!G$2:G$35) -> 667 | R6: Volume Sold
A7: Total Units On Order | B7: =SUM(Inventory_Data!H2:H35) -> 320 | H7: Filtered Sales Revenue | I7: =IF(OR(I$1="All Categories", I$1=""), SUM(Sales_Orders!I$2:I$35), SUMIFS(Sales_Orders!I$2:I$35, Sales_Orders!E$2:E$35, I$1)) -> 8719.74 | K7: =IFERROR(__xludf.DUMMYFUNCTION("IFERROR(INDEX(FILTER(Inventory_Data!B$2:B$35, (Inventory_Data!A$2:A$35<>"""") * IF(OR(I$1=""All Categories"", I$1=""""), 1, (Inventory_Data!C$2:C$35=I$1))), 6), ""-"")"),"Velvet Accent Living Chair") -> Velvet Accent Living Chair | L7: =IFERROR(__xludf.DUMMYFUNCTION("IFERROR(INDEX(FILTER(Inventory_Data!F$2:F$35, (Inventory_Data!A$2:A$35<>"""") * IF(OR(I$1=""All Categories"", I$1=""""), 1, (Inventory_Data!C$2:C$35=I$1))), 6), 0)"),14.0) -> 14 | M7: =IFERROR(__xludf.DUMMYFUNCTION("IFERROR(INDEX(FILTER(Inventory_Data!G$2:G$35, (Inventory_Data!A$2:A$35<>"""") * IF(OR(I$1=""All Categories"", I$1=""""), 1, (Inventory_Data!C$2:C$35=I$1))), 6), 0)"),20.0) -> 20 | N7: =IFERROR(__xludf.DUMMYFUNCTION("IFERROR(INDEX(FILTER(Inventory_Data!K$2:K$35, (Inventory_Data!A$2:A$35<>"""") * IF(OR(I$1=""All Categories"", I$1=""""), 1, (Inventory_Data!C$2:C$35=I$1))), 6), ""-"")"),"Needs Reorder") -> Needs Reorder | O7: =IF(K7="-", 0, IFERROR(SUMIF(Sales_Orders!D$2:D$35, K7, Sales_Orders!G$2:G$35), 0)) -> 5 | P7: Avg Order Value | Q7: =IF(COUNTA(Sales_Orders!A$2:A$35)>0, Q2/COUNTA(Sales_Orders!A$2:A$35), 0) -> 1042.7791 | R7: AOV
H8: Filtered Gross Profit | I8: =IF(OR(I$1="All Categories", I$1=""), SUM(Sales_Orders!K$2:K$35), SUMIFS(Sales_Orders!K$2:K$35, Sales_Orders!E$2:E$35, I$1)) -> 4792.74 | K8: =IFERROR(__xludf.DUMMYFUNCTION("IFERROR(INDEX(FILTER(Inventory_Data!B$2:B$35, (Inventory_Data!A$2:A$35<>"""") * IF(OR(I$1=""All Categories"", I$1=""""), 1, (Inventory_Data!C$2:C$35=I$1))), 7), ""-"")"),"Dual Monitor Adjustable Arm") -> Dual Monitor Adjustable Arm | L8: =IFERROR(__xludf.DUMMYFUNCTION("IFERROR(INDEX(FILTER(Inventory_Data!F$2:F$35, (Inventory_Data!A$2:A$35<>"""") * IF(OR(I$1=""All Categories"", I$1=""""), 1, (Inventory_Data!C$2:C$35=I$1))), 7), 0)"),18.0) -> 18 | M8: =IFERROR(__xludf.DUMMYFUNCTION("IFERROR(INDEX(FILTER(Inventory_Data!G$2:G$35, (Inventory_Data!A$2:A$35<>"""") * IF(OR(I$1=""All Categories"", I$1=""""), 1, (Inventory_Data!C$2:C$35=I$1))), 7), 0)"),25.0) -> 25 | N8: =IFERROR(__xludf.DUMMYFUNCTION("IFERROR(INDEX(FILTER(Inventory_Data!K$2:K$35, (Inventory_Data!A$2:A$35<>"""") * IF(OR(I$1=""All Categories"", I$1=""""), 1, (Inventory_Data!C$2:C$35=I$1))), 7), ""-"")"),"Needs Reorder") -> Needs Reorder | O8: =IF(K8="-", 0, IFERROR(SUMIF(Sales_Orders!D$2:D$35, K8, Sales_Orders!G$2:G$35), 0)) -> 8 | P8: Supplier Fulfillment Rate | Q8: =AVERAGE(Suppliers_Data!E$2:E$9) -> 0.94375 | R8: On-Time %
H9: Filtered Gross Profit % | I9: =IF(I7>0, I8/I7, 0) -> 0.54964254 | K9: =IFERROR(__xludf.DUMMYFUNCTION("IFERROR(INDEX(FILTER(Inventory_Data!B$2:B$35, (Inventory_Data!A$2:A$35<>"""") * IF(OR(I$1=""All Categories"", I$1=""""), 1, (Inventory_Data!C$2:C$35=I$1))), 8), ""-"")"),"Bamboo Memory Foam Pillow") -> Bamboo Memory Foam Pillow | L9: =IFERROR(__xludf.DUMMYFUNCTION("IFERROR(INDEX(FILTER(Inventory_Data!F$2:F$35, (Inventory_Data!A$2:A$35<>"""") * IF(OR(I$1=""All Categories"", I$1=""""), 1, (Inventory_Data!C$2:C$35=I$1))), 8), 0)"),60.0) -> 60 | M9: =IFERROR(__xludf.DUMMYFUNCTION("IFERROR(INDEX(FILTER(Inventory_Data!G$2:G$35, (Inventory_Data!A$2:A$35<>"""") * IF(OR(I$1=""All Categories"", I$1=""""), 1, (Inventory_Data!C$2:C$35=I$1))), 8), 0)"),30.0) -> 30 | N9: =IFERROR(__xludf.DUMMYFUNCTION("IFERROR(INDEX(FILTER(Inventory_Data!K$2:K$35, (Inventory_Data!A$2:A$35<>"""") * IF(OR(I$1=""All Categories"", I$1=""""), 1, (Inventory_Data!C$2:C$35=I$1))), 8), ""-"")"),"Sufficient") -> Sufficient | O9: =IF(K9="-", 0, IFERROR(SUMIF(Sales_Orders!D$2:D$35, K9, Sales_Orders!G$2:G$35), 0)) -> 18 | P9: Active Supplier Orders | Q9: =SUM(Suppliers_Data!G$2:G$9) -> 17 | R9: In Procurement
H10: Filtered Units Sold | I10: =IF(OR(I$1="All Categories", I$1=""), SUM(Sales_Orders!G$2:G$35), SUMIFS(Sales_Orders!G$2:G$35, Sales_Orders!E$2:E$35, I$1)) -> 84 | K10: =IFERROR(__xludf.DUMMYFUNCTION("IFERROR(INDEX(FILTER(Inventory_Data!B$2:B$35, (Inventory_Data!A$2:A$35<>"""") * IF(OR(I$1=""All Categories"", I$1=""""), 1, (Inventory_Data!C$2:C$35=I$1))), 9), ""-"")"),"-") -> - | L10: =IFERROR(__xludf.DUMMYFUNCTION("IFERROR(INDEX(FILTER(Inventory_Data!F$2:F$35, (Inventory_Data!A$2:A$35<>"""") * IF(OR(I$1=""All Categories"", I$1=""""), 1, (Inventory_Data!C$2:C$35=I$1))), 9), 0)"),0.0) -> 0 | M10: =IFERROR(__xludf.DUMMYFUNCTION("IFERROR(INDEX(FILTER(Inventory_Data!G$2:G$35, (Inventory_Data!A$2:A$35<>"""") * IF(OR(I$1=""All Categories"", I$1=""""), 1, (Inventory_Data!C$2:C$35=I$1))), 9), 0)"),0.0) -> 0 | N10: =IFERROR(__xludf.DUMMYFUNCTION("IFERROR(INDEX(FILTER(Inventory_Data!K$2:K$35, (Inventory_Data!A$2:A$35<>"""") * IF(OR(I$1=""All Categories"", I$1=""""), 1, (Inventory_Data!C$2:C$35=I$1))), 9), ""-"")"),"-") -> - | O10: =IF(K10="-", 0, IFERROR(SUMIF(Sales_Orders!D$2:D$35, K10, Sales_Orders!G$2:G$35), 0)) -> 0 | P10: Total Supplier Spend | Q10: =SUM(Suppliers_Data!H$2:H$9) -> 128800 | R10: Procurement Spend
K11: =IFERROR(__xludf.DUMMYFUNCTION("IFERROR(INDEX(FILTER(Inventory_Data!B$2:B$35, (Inventory_Data!A$2:A$35<>"""") * IF(OR(I$1=""All Categories"", I$1=""""), 1, (Inventory_Data!C$2:C$35=I$1))), 10), ""-"")"),"-") -> - | L11: =IFERROR(__xludf.DUMMYFUNCTION("IFERROR(INDEX(FILTER(Inventory_Data!F$2:F$35, (Inventory_Data!A$2:A$35<>"""") * IF(OR(I$1=""All Categories"", I$1=""""), 1, (Inventory_Data!C$2:C$35=I$1))), 10), 0)"),0.0) -> 0 | M11: =IFERROR(__xludf.DUMMYFUNCTION("IFERROR(INDEX(FILTER(Inventory_Data!G$2:G$35, (Inventory_Data!A$2:A$35<>"""") * IF(OR(I$1=""All Categories"", I$1=""""), 1, (Inventory_Data!C$2:C$35=I$1))), 10), 0)"),0.0) -> 0 | N11: =IFERROR(__xludf.DUMMYFUNCTION("IFERROR(INDEX(FILTER(Inventory_Data!K$2:K$35, (Inventory_Data!A$2:A$35<>"""") * IF(OR(I$1=""All Categories"", I$1=""""), 1, (Inventory_Data!C$2:C$35=I$1))), 10), ""-"")"),"-") -> - | O11: =IF(K11="-", 0, IFERROR(SUMIF(Sales_Orders!D$2:D$35, K11, Sales_Orders!G$2:G$35), 0)) -> 0
P12: Category | Q12: Category Revenue | R12: Category COGS | S12: Category Profit | T12: Category Margin % | U12: Units Sold
P13: Electronics | Q13: =SUMIFS(Sales_Orders!I$2:I$35, Sales_Orders!E$2:E$35, P13) -> 13064.38 | R13: =SUMIFS(Sales_Orders!J$2:J$35, Sales_Orders!E$2:E$35, P13) -> 6046.5 | S13: =SUMIFS(Sales_Orders!K$2:K$35, Sales_Orders!E$2:E$35, P13) -> 7017.88 | T13: =IF(Q13>0, S13/Q13, 0) -> 0.53717666 | U13: =SUMIFS(Sales_Orders!G$2:G$35, Sales_Orders!E$2:E$35, P13) -> 202
P14: Furniture | Q14: =SUMIFS(Sales_Orders!I$2:I$35, Sales_Orders!E$2:E$35, P14) -> 8719.74 | R14: =SUMIFS(Sales_Orders!J$2:J$35, Sales_Orders!E$2:E$35, P14) -> 3927 | S14: =SUMIFS(Sales_Orders!K$2:K$35, Sales_Orders!E$2:E$35, P14) -> 4792.74 | T14: =IF(Q14>0, S14/Q14, 0) -> 0.54964254 | U14: =SUMIFS(Sales_Orders!G$2:G$35, Sales_Orders!E$2:E$35, P14) -> 84
P15: Apparel | Q15: =SUMIFS(Sales_Orders!I$2:I$35, Sales_Orders!E$2:E$35, P15) -> 6505 | R15: =SUMIFS(Sales_Orders!J$2:J$35, Sales_Orders!E$2:E$35, P15) -> 2443 | S15: =SUMIFS(Sales_Orders!K$2:K$35, Sales_Orders!E$2:E$35, P15) -> 4062 | T15: =IF(Q15>0, S15/Q15, 0) -> 0.62444274 | U15: =SUMIFS(Sales_Orders!G$2:G$35, Sales_Orders!E$2:E$35, P15) -> 179
P16: Kitchenware | Q16: =SUMIFS(Sales_Orders!I$2:I$35, Sales_Orders!E$2:E$35, P16) -> 7165.37 | R16: =SUMIFS(Sales_Orders!J$2:J$35, Sales_Orders!E$2:E$35, P16) -> 2944 | S16: =SUMIFS(Sales_Orders!K$2:K$35, Sales_Orders!E$2:E$35, P16) -> 4221.37 | T16: =IF(Q16>0, S16/Q16, 0) -> 0.58913496 | U16: =SUMIFS(Sales_Orders!G$2:G$35, Sales_Orders!E$2:E$35, P16) -> 202
P17: Total | Q17: =SUM(Q13:Q16) -> 35454.49 | R17: =SUM(R13:R16) -> 15360.5 | S17: =SUM(S13:S16) -> 20093.99 | T17: =IF(Q17>0, S17/Q17, 0) -> 0.56675445 | U17: =SUM(U13:U16) -> 667

Sheet Dashboard
B2: 3D INTERACTIVE DATA ANALYTICS & OPERATIONS DASHBOARD
B3: Real-Time Multi-Dimensional Analytics across Sales, Inventory Valuation & Supplier Reliability
B9: FILTER BY CATEGORY: | D9: Furniture
I24: TOP REVENUE PRODUCTS
I25: Product Name | J25: Category | K25: Units Sold | L25: Revenue | M25: Margin % | N25: Performance
I26: Wireless Headphones | J26: Electronics | K26: 18 | L26: 2339.82 | M26: 0.5 | N26: High Performer
I27: Motorized Standing Desk | J27: Furniture | K27: 5 | L27: 1995 | M27: 0.536 | N27: High Performer
I28: Ergonomic Office Chair | J28: Furniture | K28: 8 | L28: 1996 | M28: 0.559 | N28: High Performer
I29: 4K Action Camera | J29: Electronics | K29: 10 | L29: 1699.9 | M29: 0.518 | N29: Steady Growth
I30: Solid Oak Bookshelf | J30: Furniture | K30: 6 | L30: 1194 | M30: 0.523 | N30: Steady Growth
I32: SUPPLIER PERFORMANCE SCORECARD
I33: Supplier Name | J33: Category | K33: Lead Time | L33: On-Time % | M33: Rating | N33: Fulfillment Status
I34: Apex Components Co. | J34: Electronics | K34: 7 days | L34: 0.965 | M34: 4.8 / 5.0 | N34: Preferred Vendor
I35: EcoWeave Textiles Ltd. | J35: Apparel | K35: 9 days | L35: 0.98 | M35: 4.9 / 5.0 | N35: Preferred Vendor
I36: Summit Activewear Mills | J36: Apparel | K36: 8 days | L36: 0.975 | M36: 4.8 / 5.0 | N36: Preferred Vendor
I37: Silicon Logic Devices | J37: Electronics | K37: 6 days | L37: 0.95 | M37: 4.7 / 5.0 | N37: Preferred Vendor
I38: Precision Steelworks | J38: Kitchenware | K38: 11 days | L38: 0.94 | M38: 4.6 / 5.0 | N38: Standard Vendor

Sheet Sales_Orders
A1: Order ID | B1: Date | C1: SKU | D1: Product Name | E1: Category | F1: Channel | G1: Units Sold | H1: Unit Price | I1: Revenue | J1: COGS | K1: Gross Profit
A2: ORD-2026-001 | B2: 46235 | C2: SKU-1001 | D2: =VLOOKUP(C2, Inventory_Data!A$2:C$35, 2, FALSE) -> Wireless Noise-Canceling Headphones | E2: =VLOOKUP(C2, Inventory_Data!A$2:C$35, 3, FALSE) -> Electronics | F2: Online Store | G2: 18 | H2: =VLOOKUP(C2, Inventory_Data!A$2:E$35, 5, FALSE) -> 129.99 | I2: =G2*H2 -> 2339.82 | J2: =G2*VLOOKUP(C2, Inventory_Data!A$2:D$35, 4, FALSE) -> 1170 | K2: =I2-J2 -> 1169.82
A3: ORD-2026-002 | B3: 46236 | C3: SKU-1005 | D3: =VLOOKUP(C3, Inventory_Data!A$2:C$35, 2, FALSE) -> Organic Cotton T-Shirt | E3: =VLOOKUP(C3, Inventory_Data!A$2:C$35, 3, FALSE) -> Apparel | F3: Marketplace | G3: 45 | H3: =VLOOKUP(C3, Inventory_Data!A$2:E$35, 5, FALSE) -> 24 | I3: =G3*H3 -> 1080 | J3: =G3*VLOOKUP(C3, Inventory_Data!A$2:D$35, 4, FALSE) -> 369 | K3: =I3-J3 -> 711
A4: ORD-2026-003 | B4: 46237 | C4: SKU-1003 | D4: =VLOOKUP(C4, Inventory_Data!A$2:C$35, 2, FALSE) -> Ergonomic Office Chair | E4: =VLOOKUP(C4, Inventory_Data!A$2:C$35, 3, FALSE) -> Furniture | F4: Direct B2B | G4: 8 | H4: =VLOOKUP(C4, Inventory_Data!A$2:E$35, 5, FALSE) -> 249.5 | I4: =G4*H4 -> 1996 | J4: =G4*VLOOKUP(C4, Inventory_Data!A$2:D$35, 4, FALSE) -> 880 | K4: =I4-J4 -> 1116
A5: ORD-2026-004 | B5: 46239 | C5: SKU-1007 | D5: =VLOOKUP(C5, Inventory_Data!A$2:C$35, 2, FALSE) -> Ceramic Pour-Over Coffee Maker | E5: =VLOOKUP(C5, Inventory_Data!A$2:C$35, 3, FALSE) -> Kitchenware | F5: Online Store | G5: 22 | H5: =VLOOKUP(C5, Inventory_Data!A$2:E$35, 5, FALSE) -> 36 | I5: =G5*H5 -> 792 | J5: =G5*VLOOKUP(C5, Inventory_Data!A$2:D$35, 4, FALSE) -> 319 | K5: =I5-J5 -> 473
A6: ORD-2026-005 | B6: 46240 | C6: SKU-1010 | D6: =VLOOKUP(C6, Inventory_Data!A$2:C$35, 2, FALSE) -> Ultra-Fast USB-C Charging Hub | E6: =VLOOKUP(C6, Inventory_Data!A$2:C$35, 3, FALSE) -> Electronics | F6: Marketplace | G6: 35 | H6: =VLOOKUP(C6, Inventory_Data!A$2:E$35, 5, FALSE) -> 29.99 | I6: =G6*H6 -> 1049.65 | J6: =G6*VLOOKUP(C6, Inventory_Data!A$2:D$35, 4, FALSE) -> 437.5 | K6: =I6-J6 -> 612.15
A7: ORD-2026-006 | B7: 46242 | C7: SKU-1004 | D7: =VLOOKUP(C7, Inventory_Data!A$2:C$35, 2, FALSE) -> Motorized Standing Desk | E7: =VLOOKUP(C7, Inventory_Data!A$2:C$35, 3, FALSE) -> Furniture | F7: Direct B2B | G7: 5 | H7: =VLOOKUP(C7, Inventory_Data!A$2:E$35, 5, FALSE) -> 399 | I7: =G7*H7 -> 1995 | J7: =G7*VLOOKUP(C7, Inventory_Data!A$2:D$35, 4, FALSE) -> 925 | K7: =I7-J7 -> 1070
A8: ORD-2026-007 | B8: 46243 | C8: SKU-1006 | D8: =VLOOKUP(C8, Inventory_Data!A$2:C$35, 2, FALSE) -> Waterproof Trail Jacket | E8: =VLOOKUP(C8, Inventory_Data!A$2:C$35, 3, FALSE) -> Apparel | F8: Retail Partner | G8: 14 | H8: =VLOOKUP(C8, Inventory_Data!A$2:E$35, 5, FALSE) -> 85 | I8: =G8*H8 -> 1190 | J8: =G8*VLOOKUP(C8, Inventory_Data!A$2:D$35, 4, FALSE) -> 476 | K8: =I8-J8 -> 714
A9: ORD-2026-008 | B9: 46245 | C9: SKU-1008 | D9: =VLOOKUP(C9, Inventory_Data!A$2:C$35, 2, FALSE) -> Cast Iron Skillet 12-inch | E9: =VLOOKUP(C9, Inventory_Data!A$2:C$35, 3, FALSE) -> Kitchenware | F9: Online Store | G9: 16 | H9: =VLOOKUP(C9, Inventory_Data!A$2:E$35, 5, FALSE) -> 49.99 | I9: =G9*H9 -> 799.84 | J9: =G9*VLOOKUP(C9, Inventory_Data!A$2:D$35, 4, FALSE) -> 352 | K9: =I9-J9 -> 447.84
A10: ORD-2026-009 | B10: 46246 | C10: SKU-1002 | D10: =VLOOKUP(C10, Inventory_Data!A$2:C$35, 2, FALSE) -> Mechanical Gaming Keyboard | E10: =VLOOKUP(C10, Inventory_Data!A$2:C$35, 3, FALSE) -> Electronics | F10: Online Store | G10: 20 | H10: =VLOOKUP(C10, Inventory_Data!A$2:E$35, 5, FALSE) -> 89.99 | I10: =G10*H10 -> 1799.8 | J10: =G10*VLOOKUP(C10, Inventory_Data!A$2:D$35, 4, FALSE) -> 910 | K10: =I10-J10 -> 889.8
A11: ORD-2026-010 | B11: 46248 | C11: SKU-1011 | D11: =VLOOKUP(C11, Inventory_Data!A$2:C$35, 2, FALSE) -> Solid Oak Bookshelf 5-Tier | E11: =VLOOKUP(C11, Inventory_Data!A$2:C$35, 3, FALSE) -> Furniture | F11: Direct B2B | G11: 6 | H11: =VLOOKUP(C11, Inventory_Data!A$2:E$35, 5, FALSE) -> 199 | I11: =G11*H11 -> 1194 | J11: =G11*VLOOKUP(C11, Inventory_Data!A$2:D$35, 4, FALSE) -> 570 | K11: =I11-J11 -> 624
A12: ORD-2026-011 | B12: 46249 | C12: SKU-1020 | D12: =VLOOKUP(C12, Inventory_Data!A$2:C$35, 2, FALSE) -> Breathable Yoga Pants | E12: =VLOOKUP(C12, Inventory_Data!A$2:C$35, 3, FALSE) -> Apparel | F12: Retail Partner | G12: 28 | H12: =VLOOKUP(C12, Inventory_Data!A$2:E$35, 5, FALSE) -> 42 | I12: =G12*H12 -> 1176 | J12: =G12*VLOOKUP(C12, Inventory_Data!A$2:D$35, 4, FALSE) -> 392 | K12: =I12-J12 -> 784
A13: ORD-2026-012 | B13: 46251 | C13: SKU-1021 | D13: =VLOOKUP(C13, Inventory_Data!A$2:C$35, 2, FALSE) -> Insulated Stainless Tumbler 32oz | E13: =VLOOKUP(C13, Inventory_Data!A$2:C$35, 3, FALSE) -> Kitchenware | F13: Marketplace | G13: 40 | H13: =VLOOKUP(C13, Inventory_Data!A$2:E$35, 5, FALSE) -> 24.99 | I13: =G13*H13 -> 999.6 | J13: =G13*VLOOKUP(C13, Inventory_Data!A$2:D$35, 4, FALSE) -> 380 | K13: =I13-J13 -> 619.6
... A35: ORD-2026-034 | B35: 46290 | C35: SKU-1014 | D35: =VLOOKUP(C35, Inventory_Data!A$2:C$35, 2, FALSE) -> Merino Wool Winter Beanie | E35: =VLOOKUP(C35, Inventory_Data!A$2:C$35, 3, FALSE) -> Apparel | F35: Online Store | G35: 36 | H35: =VLOOKUP(C35, Inventory_Data!A$2:E$35, 5, FALSE) -> 18.5 | I35: =G35*H35 -> 666 | J35: =G35*VLOOKUP(C35, Inventory_Data!A$2:D$35, 4, FALSE) -> 234 | K35: =I35-J35 -> 432

Sheet Suppliers_Data
A1: Supplier ID | B1: Supplier Name | C1: Category | D1: Lead Time Days | E1: On-Time Delivery % | F1: Reliability Rating | G1: Active Orders | H1: Total Spend
A2: SUP-101 | B2: Apex Components Co. | C2: Electronics | D2: 7 | E2: 0.965 | F2: 4.8 | G2: 3 | H2: 24500
A3: SUP-102 | B3: Nordic Timber & Metal | C3: Furniture | D3: 14 | E3: 0.92 | F3: 4.5 | G3: 2 | H3: 18750
A4: SUP-103 | B4: EcoWeave Textiles Ltd. | C4: Apparel | D4: 9 | E4: 0.98 | F4: 4.9 | G4: 1 | H4: 14200
A5: SUP-104 | B5: Precision Steelworks | C5: Kitchenware | D5: 11 | E5: 0.94 | F5: 4.6 | G5: 2 | H5: 11800
A6: SUP-105 | B6: Silicon Logic Devices | C6: Electronics | D6: 6 | E6: 0.95 | F6: 4.7 | G6: 4 | H6: 21900
A7: SUP-106 | B7: ComfortCraft Studio | C7: Furniture | D7: 16 | E7: 0.885 | F7: 4.2 | G7: 2 | H7: 15400
A8: SUP-107 | B8: Summit Activewear Mills | C8: Apparel | D8: 8 | E8: 0.975 | F8: 4.8 | G8: 1 | H8: 9600
A9: SUP-108 | B9: Artisan Culinary Supply | C9: Kitchenware | D9: 10 | E9: 0.935 | F9: 4.5 | G9: 2 | H9: 12650
A10: TOTAL / AVERAGE | B10: - | C10: - | D10: =ROUND(AVERAGE(D2:D9), 1) -> 10.1 | E10: =AVERAGE(E2:E9) -> 0.94375 | F10: =ROUND(AVERAGE(F2:F9), 2) -> 4.63 | G10: =SUM(G2:G9) -> 17 | H10: =SUM(H2:H9) -> 128800
